flexigurator/__init__.py
flexigurator/config_patch.py
flexigurator/config_versions.py
flexigurator/form/__init__.py
flexigurator/form/form.py
flexigurator/form/jinja_templates/config_form.html
flexigurator/form/jinja_templates/index.html
flexigurator/placeholder.py
flexigurator/py.typed
flexigurator-0.5.3.dist-info/METADATA
flexigurator-0.5.3.dist-info/WHEEL
flexigurator-0.5.3.dist-info/RECORD
