Metadata-Version: 2.1
Name: flexigurator
Version: 0.5.3
Summary: Python Configuration solution.
Author: Thomas Bos
Author-email: thymer.bos217@gmail.com
Requires-Python: >=3.11,<4.0
Classifier: Programming Language :: Python :: 3
Classifier: Programming Language :: Python :: 3.11
Provides-Extra: form
Requires-Dist: confz (>=1.8.1,<2.0.0)
Requires-Dist: fastapi (>=0.103.2,<0.104.0) ; extra == "form"
Requires-Dist: jinja2 (>=3.1.2,<4.0.0) ; extra == "form"
Requires-Dist: mmh3 (>=4.0.1,<5.0.0) ; extra == "form"
Requires-Dist: pydantic (>=1.10.8,<2.0.0)
Requires-Dist: pyyaml (>=6.0,<7.0)
